[{"name":"NoAlways","comment":"\n\n@docs rule\n\n","unions":[],"aliases":[],"values":[{"name":"rule","comment":" Forbid the use of `always`.\n\n    config : List Rule\n    config =\n        [ NoAlways.rule\n        ]\n\nUse anonymous function `\\_ ->` over `always`.\n\nIt's more concise, more recognizable as a function, and makes it easier to change your mind later and name the argument.\n\n\n## Failure\n\n    -- Don't do this --\n    List.map (always 0) [ 1, 2, 3, 4 ]\n\n\n## Success\n\n    -- Instead do this --\n    List.map (\\_ -> 0) [ 1, 2, 3, 4 ]\n\n","type":"Review.Rule.Rule"}],"binops":[]}]