{
  "fetched_at": "2026-03-24T15:09:20.843Z",
  "stargazers_count": 24,
  "last_commit_at": "2022-12-30T22:58:57Z",
  "open_issues": {
    "count": 3,
    "min_days": 1981,
    "max_days": 2138,
    "avg_days": 2060,
    "items": [
      {
        "number": 12,
        "created_at": "2020-10-20T23:35:08Z",
        "last_comment_at": "2020-10-21T00:24:18Z",
        "last_comment_by_maintainer": true
      },
      {
        "number": 11,
        "created_at": "2020-08-02T16:54:12Z",
        "last_comment_at": "2020-08-02T17:07:22Z",
        "last_comment_by_maintainer": true
      },
      {
        "number": 10,
        "created_at": "2020-05-16T23:55:33Z",
        "last_comment_at": "2020-08-02T17:08:50Z",
        "last_comment_by_maintainer": true
      }
    ]
  },
  "open_prs": {
    "count": 0,
    "min_days": 0,
    "max_days": 0,
    "avg_days": 0,
    "items": []
  }
}